pyasic_rs-0.1.4.dist-info/METADATA
pyasic_rs-0.1.4.dist-info/WHEEL
pyasic_rs-0.1.4.dist-info/licenses/LICENSE.txt
pyasic_rs/__init__.py
pyasic_rs/asic_rs.pypy311-pp73-ppc_64-linux-gnu.so
pyasic_rs/data.py
pyasic_rs/factory.py
pyasic_rs/miner.py
pyasic_rs-0.1.4.dist-info/RECORD
