Metadata-Version: 2.4
Name: pyasic_rs
Version: 0.1.4
Classifier: Development Status :: 4 - Beta
Classifier: Intended Audience :: Developers
Classifier: License :: OSI Approved :: Apache Software License
Classifier: Programming Language :: Python
Classifier: Programming Language :: Python :: 3
Classifier: Programming Language :: Python :: 3.11
Classifier: Programming Language :: Python :: 3.12
Classifier: Programming Language :: Python :: 3.13
Requires-Dist: pydantic
License-File: LICENSE.txt
Summary: Python bindings for asic-rs
Keywords: python,asic,bitcoin,whatsminer,antminer,braiins-os,vnish,luxos,bitaxe
Author-email: Brett Rowan <121075405+b-rowan@users.noreply.github.com>
License-Expression: Apache 2.0
Requires-Python: >=3.11, <4.0
